woxchain/__init__.py
woxchain/client.py
woxchain_python-0.1.0.dist-info/licenses/LICENSE
woxchain_python-0.1.0.dist-info/METADATA
woxchain_python-0.1.0.dist-info/WHEEL
woxchain_python-0.1.0.dist-info/top_level.txt
woxchain_python-0.1.0.dist-info/RECORD
